odoo/addons/sale_template_operating_unit/README.rst
odoo/addons/sale_template_operating_unit/__init__.py
odoo/addons/sale_template_operating_unit/__manifest__.py
odoo/addons/sale_template_operating_unit/i18n/it.po
odoo/addons/sale_template_operating_unit/i18n/sale_template_operating_unit.pot
odoo/addons/sale_template_operating_unit/models/__init__.py
odoo/addons/sale_template_operating_unit/models/sale_order_template.py
odoo/addons/sale_template_operating_unit/readme/CONTRIBUTORS.rst
odoo/addons/sale_template_operating_unit/readme/DESCRIPTION.rst
odoo/addons/sale_template_operating_unit/readme/USAGE.rst
odoo/addons/sale_template_operating_unit/security/sale_template_security.xml
odoo/addons/sale_template_operating_unit/static/description/icon.png
odoo/addons/sale_template_operating_unit/static/description/index.html
odoo/addons/sale_template_operating_unit/views/sale_template_view.xml
odoo14_addon_sale_template_operating_unit-14.0.1.0.1.dev8.dist-info/METADATA
odoo14_addon_sale_template_operating_unit-14.0.1.0.1.dev8.dist-info/WHEEL
odoo14_addon_sale_template_operating_unit-14.0.1.0.1.dev8.dist-info/top_level.txt
odoo14_addon_sale_template_operating_unit-14.0.1.0.1.dev8.dist-info/RECORD
